polymesh/__init__.py
polymesh/abcdata.py
polymesh/akwrap.py
polymesh/base.py
polymesh/cell.py
polymesh/celldata.py
polymesh/config.py
polymesh/examples.py
polymesh/extrude.py
polymesh/grid.py
polymesh/helpers.py
polymesh/line.py
polymesh/linedata.py
polymesh/mesh1d.py
polymesh/pointdata.py
polymesh/polydata.py
polymesh/polygon.py
polymesh/polyhedron.py
polymesh/pop.py
polymesh/recipes.py
polymesh/section.py
polymesh/tetmesh.py
polymesh/tetrahedralize.py
polymesh/tile.py
polymesh/topoarray.py
polymesh/triang.py
polymesh/trimesh.py
polymesh/voxelize.py
polymesh/vtkcelltypes.py
polymesh/vtkutils.py
polymesh/cells/__init__.py
polymesh/cells/h27.py
polymesh/cells/h8.py
polymesh/cells/l2.py
polymesh/cells/l3.py
polymesh/cells/q4.py
polymesh/cells/q9.py
polymesh/cells/t3.py
polymesh/cells/t6.py
polymesh/cells/tet10.py
polymesh/cells/tet4.py
polymesh/cells/w18.py
polymesh/cells/w6.py
polymesh/io/__init__.py
polymesh/io/inp2stl.py
polymesh/io/io.py
polymesh/space/__init__.py
polymesh/space/frame.py
polymesh/space/point.py
polymesh/space/pointcloud.py
polymesh/utils/__init__.py
polymesh/utils/colors.py
polymesh/utils/knn.py
polymesh/utils/locate.py
polymesh/utils/space.py
polymesh/utils/tet.py
polymesh/utils/topodata.py
polymesh/utils/tri.py
polymesh/utils/utils.py
polymesh/utils/cells/__init__.py
polymesh/utils/cells/gauss.py
polymesh/utils/cells/h27.py
polymesh/utils/cells/h8.py
polymesh/utils/cells/l2.py
polymesh/utils/cells/l3.py
polymesh/utils/cells/q4.py
polymesh/utils/cells/q9.py
polymesh/utils/cells/t3.py
polymesh/utils/cells/t6.py
polymesh/utils/cells/tet10.py
polymesh/utils/cells/tet4.py
polymesh/utils/cells/utils.py
polymesh/utils/cells/w18.py
polymesh/utils/cells/w6.py
polymesh/utils/topology/__init__.py
polymesh/utils/topology/topo.py
polymesh/utils/topology/tr.py
polymesh-0.0.25.dist-info/LICENSE
polymesh-0.0.25.dist-info/METADATA
polymesh-0.0.25.dist-info/WHEEL
polymesh-0.0.25.dist-info/top_level.txt
polymesh-0.0.25.dist-info/RECORD
