Metadata-Version: 2.1
Name: polymesh
Version: 0.0.25
Summary: A Python package to build, manipulate and analyze polygonal meshes.
Home-page: https://github.com/dewloosh/PolyMesh
Download-URL: https://github.com/dewloosh/PolyMesh/archive/refs/tags/v0.0.25.zip
Author: Bence Balogh
Author-email: dewloosh@gmail.com
Maintainer: Bence Balogh
Maintainer-email: dewloosh@gmail.com
Classifier: Development Status :: 5 - Production/Stable
Classifier: License :: OSI Approved :: MIT License
Classifier: Programming Language :: Python :: 3.7
Classifier: Programming Language :: Python :: 3.8
Classifier: Programming Language :: Python :: 3.9
Classifier: Programming Language :: Python :: 3.10
Classifier: Programming Language :: Python :: 3 :: Only
Classifier: Operating System :: OS Independent
Classifier: Topic :: Scientific/Engineering
Requires-Python: >=3.7, <3.11
License-File: LICENSE
Requires-Dist: packaging
Requires-Dist: toml
Requires-Dist: setuptools (>=65.5.1)
Requires-Dist: wheel (>=0.38.0)
Requires-Dist: linkeddeepdict (>=1.1.0)
Requires-Dist: dewloosh.core (>=1.0.21)
Requires-Dist: neumann (>=1.0.7)
Requires-Dist: fsspec (>=2023.1.0)
Requires-Dist: sectionproperties (>=2.1.3)
Requires-Dist: meshio
Provides-Extra: all
Requires-Dist: pyvista ; extra == 'all'
Requires-Dist: k3d ; extra == 'all'
Requires-Dist: vtk ; extra == 'all'
Requires-Dist: networkx ; extra == 'all'
Requires-Dist: pyarrow ; extra == 'all'
Requires-Dist: tetgen ; extra == 'all'
Provides-Extra: testing
Requires-Dist: pytest ; extra == 'testing'
Requires-Dist: pandas ; extra == 'testing'
Requires-Dist: pyarrow ; extra == 'testing'
Requires-Dist: networkx ; extra == 'testing'
Requires-Dist: pyvista ; extra == 'testing'
Requires-Dist: tetgen ; extra == 'testing'
